BackTranslation/__init__.py
BackTranslation/languages.py
BackTranslation/translated.py
BackTranslation/translation.py
BackTranslation/translation_Baidu.py
BackTranslation-0.3.1.dist-info/LICENSE
BackTranslation-0.3.1.dist-info/METADATA
BackTranslation-0.3.1.dist-info/WHEEL
BackTranslation-0.3.1.dist-info/top_level.txt
BackTranslation-0.3.1.dist-info/RECORD
