Metadata-Version: 2.1
Name: BackTranslation
Version: 0.3.1
Summary: Back translation for Natural Language Processing (NLP) using Google Translate
Home-page: https://github.com/hhhwwwuuu/BackTranslation
Author: Zhiqiang Wu
Author-email: wzq0515@gmail.com
License: MIT
Keywords: Translation,NLP,back-translation
Platform: UNKNOWN
Classifier: Development Status :: 4 - Beta
Classifier: Operating System :: OS Independent
Classifier: License :: OSI Approved :: MIT License
Classifier: Programming Language :: Python :: 3.0
Requires-Python: >=3
Requires-Dist: googletrans (==4.0.0rc1)
Requires-Dist: nltk
